alal/__init__.py
alal/base.py
alal/model.py
alal/card/__init__.py
alal/card/model.py
alal/card/service.py
alal/cardUser/__init__.py
alal/cardUser/model.py
alal/cardUser/service.py
alal/dispute/__init__.py
alal/dispute/model.py
alal/dispute/service.py
alal/exceptions/__init__.py
alal/exceptions/exceptions.py
alal/transaction/__init__.py
alal/transaction/model.py
alal/transaction/service.py
alal-1.0.0.dist-info/METADATA
alal-1.0.0.dist-info/WHEEL
alal-1.0.0.dist-info/top_level.txt
alal-1.0.0.dist-info/RECORD
