Metadata-Version: 2.1
Name: alal
Version: 1.0.0
Summary: Python SDk for Alal's API
Home-page: https://github.com/ALAL-Community/alal-python
Author: Alal
Author-email: info@saalal.com
License: MIT
Classifier: License :: OSI Approved :: MIT License
Classifier: Programming Language :: Python :: 3
Classifier: Programming Language :: Python :: 3.6
Classifier: Programming Language :: Python :: 3.7
Requires-Python: >=3.6
Requires-Dist: requests
